etc/ibm-vpc-ray-connector/defaults.yaml
etc/ibm-vpc-ray-connector/example-minimal.yaml
vpc/__init__.py
vpc/node_provider.py
ibm_vpc_ray_connector-1.0.0b75.dist-info/LICENSE
ibm_vpc_ray_connector-1.0.0b75.dist-info/METADATA
ibm_vpc_ray_connector-1.0.0b75.dist-info/WHEEL
ibm_vpc_ray_connector-1.0.0b75.dist-info/top_level.txt
ibm_vpc_ray_connector-1.0.0b75.dist-info/RECORD
