Metadata-Version: 2.1
Name: ibm-vpc-ray-connector
Version: 1.0.0b75
Summary: IBM VPC connector for Ray
Home-page: https://github.com/project-codeflare/ibm-vpc-ray-connector
Author: kpavel, cohen-j-omer
Author-email: omer.cohen@ibm.com
Classifier: Programming Language :: Python :: 3
Requires-Python: >=3.6
License-File: LICENSE
Requires-Dist: ibm-vpc
